{
  "parent": "extrabotany:main/ego_defeat",
  "criteria": {
    "buddhist_relics_obtain": {
      "conditions": {
        "items": [
          {
            "items": [
              "extrabotany:buddhist_relics"
            ]
          }
        ]
      },
      "trigger": "minecraft:inventory_changed"
    }
  },
  "display": {
    "announce_to_chat": true,
    "description": {
      "translate": "advancement.extrabotany.buddhist_relics_obtain.desc"
    },
    "frame": "challenge",
    "hidden": false,
    "icon": {
      "item": "extrabotany:buddhist_relics"
    },
    "show_toast": true,
    "title": {
      "translate": "advancement.extrabotany.buddhist_relics_obtain.title"
    }
  },
  "requirements": [
    [
      "buddhist_relics_obtain"
    ]
  ],
  "sends_telemetry_event": true
}