{
  "type": "botania:runic_altar",
  "ingredients": [
    {
      "item": "botania:gaia_ingot"
    },
    {
      "item": "botania:gaia_ingot"
    },
    {
      "item": "botania:gaia_ingot"
    },
    {
      "item": "botania:gaia_ingot"
    },
    {
      "item": "botania:life_essence"
    },
    {
      "item": "botania:life_essence"
    },
    {
      "item": "extrabotany:gilded_mashed_potato"
    },
    {
      "item": "extrabotany:hero_medal"
    }
  ],
  "mana": 1000000,
  "output": {
    "item": "extrabotany:orichalcos"
  }
}